MANIFEST.in
README.md
requirements.txt
setup.py
same/Api.py
same/Channel.py
same/Client.py
same/Geo.py
same/Robot.py
same/Sense.py
same/User.py
same/__int__.py
same/cli.py
same.egg-info/PKG-INFO
same.egg-info/SOURCES.txt
same.egg-info/dependency_links.txt
same.egg-info/entry_points.txt
same.egg-info/requires.txt
same.egg-info/top_level.txt