Metadata-Version: 1.0
Name: same
Version: 0.0.1
Summary: same shell client
Home-page: https://github.com/acrazing/same-api
Author: acrazing
Author-email: joking.young@gmail.com
License: MIT
Keywords: same client api
Platform: UNKNOWN
